yangsrunner/__init__.py
yangsrunner/run.py
yangsrunner/common/__init__.py
yangsrunner/common/utils.py
yangsrunner/simple/__init__.py
yangsrunner/simple/executor.py
yangsrunner-0.2.1.dist-info/METADATA
yangsrunner-0.2.1.dist-info/RECORD
yangsrunner-0.2.1.dist-info/WHEEL
yangsrunner-0.2.1.dist-info/entry_points.txt
yangsrunner-0.2.1.dist-info/top_level.txt
