Metadata-Version: 2.1
Name: yangsrunner
Version: 0.2.1
Summary: Terminal Application Runner
Home-page: https://github.com/seiren87/yangsrunner
Author: seiren87
Author-email: seiren87dev@gmail.com
License: MIT
Keywords: terminal
Platform: UNKNOWN
Classifier: Intended Audience :: Developers
Classifier: Topic :: Software Development :: Libraries
Classifier: License :: OSI Approved :: MIT License
Classifier: Programming Language :: Python :: 3.5
Classifier: Programming Language :: Python :: 3.6
Requires-Python: >=3.5
Requires-Dist: yangsutil (==0.1.0)
